superwise_api/__init__.py
superwise_api/client/__init__.py
superwise_api/client/api_client.py
superwise_api/client/api_response.py
superwise_api/client/configuration.py
superwise_api/client/exceptions.py
superwise_api/client/models/page.py
superwise_api/client/models/threshold_settings.py
superwise_api/client/rest.py
superwise_api/config.py
superwise_api/entities/__init__.py
superwise_api/entities/agent.py
superwise_api/entities/base.py
superwise_api/entities/dashboard.py
superwise_api/entities/dashboard_item.py
superwise_api/entities/dataset.py
superwise_api/entities/dataset_source.py
superwise_api/entities/destination.py
superwise_api/entities/guardrails.py
superwise_api/entities/integration.py
superwise_api/entities/knowledge.py
superwise_api/entities/mcp.py
superwise_api/entities/model.py
superwise_api/entities/model_provider.py
superwise_api/entities/policy.py
superwise_api/entities/source.py
superwise_api/entities/tag.py
superwise_api/errors.py
superwise_api/models/__init__.py
superwise_api/models/agent/__init__.py
superwise_api/models/agent/agent.py
superwise_api/models/agent/feedback.py
superwise_api/models/agent/flowise.py
superwise_api/models/agent/playground.py
superwise_api/models/context/__init__.py
superwise_api/models/context/context.py
superwise_api/models/dashboard/__init__.py
superwise_api/models/dashboard/dashboard.py
superwise_api/models/dashboard/query.py
superwise_api/models/dashboard_item/__init__.py
superwise_api/models/dashboard_item/dashboard_item.py
superwise_api/models/dataset/__init__.py
superwise_api/models/dataset/dataset.py
superwise_api/models/dataset/dataset_schema.py
superwise_api/models/dataset_source/__init__.py
superwise_api/models/dataset_source/dataset_source.py
superwise_api/models/destination/__init__.py
superwise_api/models/destination/destination.py
superwise_api/models/guardrails/__init__.py
superwise_api/models/guardrails/guardrails.py
superwise_api/models/integration/__init__.py
superwise_api-4.13.2.dist-info/METADATA
superwise_api-4.13.2.dist-info/WHEEL
superwise_api-4.13.2.dist-info/RECORD
